abs_import/__init__.py
abs_import/_abs_import.py
abs_import/abs_import.py
abs_import-0.0.5.dist-info/METADATA
abs_import-0.0.5.dist-info/RECORD
abs_import-0.0.5.dist-info/WHEEL
abs_import-0.0.5.dist-info/top_level.txt
