Metadata-Version: 2.1
Name: abs-import
Version: 0.0.5
Summary: A tool for importing python modules by absolute path
Home-page: UNKNOWN
Author: Yuan Liu
Author-email: yuanl5@alumni.cmu.edu
License: UNKNOWN
Platform: UNKNOWN
Classifier: Programming Language :: Python :: 3
Classifier: License :: OSI Approved :: MIT License
Classifier: Operating System :: OS Independent
